mhlmk_test_project/__init__.py
mhlmk_test_project/_version.py
mhlmk_test_project/main.py
mhlmk_test_project/cat/__init__.py
mhlmk_test_project/cat/cat.py
mhlmk_test_project/dog/__init__.py
mhlmk_test_project/dog/dog.py
mhlmk_test_project-0.0.2.dist-info/METADATA
mhlmk_test_project-0.0.2.dist-info/WHEEL
mhlmk_test_project-0.0.2.dist-info/top_level.txt
mhlmk_test_project-0.0.2.dist-info/RECORD
